napari_imodmodel/__init__.py
napari_imodmodel/_reader.py
napari_imodmodel/_sample_data.py
napari_imodmodel/napari.yaml
napari_imodmodel/_tests/__init__.py
napari_imodmodel/_tests/test_reader.py
napari_imodmodel-1.0.2.dist-info/LICENSE
napari_imodmodel-1.0.2.dist-info/METADATA
napari_imodmodel-1.0.2.dist-info/WHEEL
napari_imodmodel-1.0.2.dist-info/entry_points.txt
napari_imodmodel-1.0.2.dist-info/top_level.txt
napari_imodmodel-1.0.2.dist-info/RECORD
