Metadata-Version: 2.1
Name: napari-imodmodel
Version: 1.0.2
Summary: Open IMOD model files in napari
Home-page: https://github.com/MoritzWM/napari-imodmodel
Author: Moritz Wachsmuth-Melm
Author-email: mail@moritzwm.de
License: BSD-3-Clause
Project-URL: Bug Tracker, https://github.com/MoritzWM/napari-imodmodel/issues
Project-URL: Documentation, https://github.com/MoritzWM/napari-imodmodel#README.md
Project-URL: Source Code, https://github.com/MoritzWM/napari-imodmodel
Project-URL: User Support, https://github.com/MoritzWM/napari-imodmodel/issues
Classifier: Framework :: napari
Classifier: Intended Audience :: Developers
Classifier: License :: OSI Approved :: BSD License
Classifier: Operating System :: OS Independent
Classifier: Programming Language :: Python
Classifier: Programming Language :: Python :: 3
Classifier: Programming Language :: Python :: 3 :: Only
Classifier: Programming Language :: Python :: 3.8
Classifier: Programming Language :: Python :: 3.9
Classifier: Programming Language :: Python :: 3.10
Classifier: Topic :: Scientific/Engineering :: Image Processing
Requires-Python: >=3.8
License-File: LICENSE
Requires-Dist: numpy
Requires-Dist: imodmodel
Provides-Extra: testing
Requires-Dist: tox ; extra == 'testing'
Requires-Dist: pytest ; extra == 'testing'
Requires-Dist: pytest-cov ; extra == 'testing'
